{
  "id": "boku",
  "title": "Boku",
  "link": "http://www.boku.com/merchants/boku-solutions/",
  "image": "https://encrypted-tbn1.gstatic.com/images?q=tbn:ANd9GcSKXeuSh5avM_-tGkpeuHE0tagHlLhH7enu-kGqynf9VL0N9zaMBw",
  "author": {
    "name": "boku"
  },
  "tags": [
    "Creat",
    "System",
    "Mobile",
    "Subscribers"
  ],
  "description": "Boku was born out of a desire to create a frictionless payment system allowing a mobile phone number to be used as a safe and secure payment instrument. In 2009, we partnered with mobile operators around the world to enable their subscribers to purchase virtual goods simply using their mobile number. - See more at: http://www.boku.com/about/#sthash.m59qva27.dpuf"
}