{
  "id": "olapic",
  "title": "Olapic",
  "link": "https://www.olapic.com/",
  "image": "https://encrypted-tbn0.gstatic.com/images?q=tbn:ANd9GcQN76fJ_eyCmnphqNxoaaRr5seqj2eolHKtfdBXroPZhgyvvRG2eQ",
  "author": {
    "name": "Olapic"
  },
  "tags": [
    "Measuring",
    "Ecommerce",
    "Publishers"
  ],
  "description": "Olapic is the leading Visual Commerce platform for collecting, curating, showcasing and measuring crowdsourced photos and videos. Our platform provides ecommerce retailers, brands and publishers with tools to engage their customers and support a strong community built on visual content. Olapic leverages photos and videos from Facebook, Twitter, Instagram, and more and makes them shoppable. "
}