{
  "id": "paysbuy",
  "title": "Paysbuy",
  "link": "https://www.paysbuy.com/developers.aspx?l=e",
  "image": "https://encrypted-tbn0.gstatic.com/images?q=tbn:ANd9GcSzfiBXkgY6YvdzIQRE1dTIOQ1HC-S7aSQtCwEtYVjTN_fsoe7t",
  "author": {
    "name": "Paysbuy"
  },
  "tags": [
    "Online",
    "Service",
    "Processing"
  ],
  "description": "PAYSBUY is a leading online payment and e-wallet service in Thailand, providing online payment processing with a variety of payment channels, including credit cards, bank online direct debits, cash at counters (at 7-Eleven, Tesco Lotus and TOT) and pre-funded e-wallet. "
}