{
  "id": "crm",
  "title": "CRM",
  "link": "http://crmtext.com/docs/",
  "image": "http://crmtext.com//wp-content/uploads/2013/10/logo1.png",
  "author": {
    "name": "CRM Text Solutions"
  },
  "tags": [
    "Provides",
    "Access",
    "Channel"
  ],
  "description": "CRM Text Solutions provides access to our patented stack of common short codes via our short code API. Within hours you can add real-time, two-way text messaging to your software applications and open a new sales channel to your customer base. "
}