{
  "id": "time-reports",
  "title": "Time Reports",
  "link": "http://developers.odesk.com/w/page/12364017/Time%20Reports%20API",
  "author": {
    "name": "Odeskdevelopers"
  },
  "tags": [
    "Language",
    "Reports",
    "Company",
    "Details"
  ],
  "description": "The Time Reports API uses the Google Visualization APIs query language to run detailed reports on a user's team, company, as well as \nprovider specific detail. In order to use the Reports API you need to understand the data model accessible as well as the supported Google query language elements."
}